{
  "_class": "shapePath",
  "booleanOperation": -1,
  "do_objectID": "4A7A8396-DAA7-4E4F-AAE4-63553286016D",
  "edited": true,
  "exportOptions": {
    "_class": "exportOptions",
    "exportFormats": [
    ],
    "includedLayerIds": [
    ],
    "layerOptions": 0,
    "shouldTrim": false
  },
  "frame": {
    "_class": "rect",
    "constrainProportions": false,
    "height": 85,
    "width": 819,
    "x": 0,
    "y": 0
  },
  "isClosed": false,
  "isFlippedHorizontal": false,
  "isFlippedVertical": false,
  "isLocked": false,
  "isVisible": true,
  "layerListExpandedType": 0,
  "name": "Path",
  "nameIsFixed": false,
  "pointRadiusBehaviour": 1,
  "points": [
    {
      "_class": "curvePoint",
      "cornerRadius": 0,
      "curveFrom": "{0.87501296176279975, 1}",
      "curveMode": 4,
      "curveTo": "{1, 1}",
      "hasCurveFrom": true,
      "hasCurveTo": false,
      "point": "{1, 1}"
    },
    {
      "_class": "curvePoint",
      "cornerRadius": 0,
      "curveFrom": "{0.62501944264419973, 0}",
      "curveMode": 2,
      "curveTo": "{0.87501296176279975, 0}",
      "hasCurveFrom": true,
      "hasCurveTo": true,
      "point": "{0.75001620220349974, 0}"
    },
    {
      "_class": "curvePoint",
      "cornerRadius": 0,
      "curveFrom": "{0.37501620220349968, 0.67069938573789412}",
      "curveMode": 2,
      "curveTo": "{0.62501620220349963, 0.67069938573789412}",
      "hasCurveFrom": true,
      "hasCurveTo": true,
      "point": "{0.50001620220349963, 0.67069938573789412}"
    },
    {
      "_class": "curvePoint",
      "cornerRadius": 0,
      "curveFrom": "{0.12500648088139987, 0}",
      "curveMode": 2,
      "curveTo": "{0.37501296176279975, 0}",
      "hasCurveFrom": true,
      "hasCurveTo": true,
      "point": "{0.25000972132209981, 0}"
    },
    {
      "_class": "curvePoint",
      "cornerRadius": 0,
      "curveFrom": "{0, 0.77437560412834039}",
      "curveMode": 4,
      "curveTo": "{0.12500324044069994, 0.77437560412834039}",
      "hasCurveFrom": false,
      "hasCurveTo": true,
      "point": "{0, 0.77437560412834039}"
    }
  ],
  "resizingConstraint": 63,
  "resizingType": 0,
  "rotation": 0,
  "shouldBreakMaskChain": false
}