{
  "_class": "group",
  "do_objectID": "88934C80-FABA-4A4F-B570-2EF32FE21AE7",
  "exportOptions": {
    "_class": "exportOptions",
    "exportFormats": [
    ],
    "includedLayerIds": [
    ],
    "layerOptions": 0,
    "shouldTrim": false
  },
  "frame": {
    "_class": "rect",
    "constrainProportions": false,
    "height": 156,
    "width": 344,
    "x": 0,
    "y": 0
  },
  "hasClickThrough": false,
  "isFlippedHorizontal": false,
  "isFlippedVertical": false,
  "isLocked": false,
  "isVisible": true,
  "layerListExpandedType": 2,
  "layers": [
    {
      "class": "shapeGroup",
      "id": "C56F7D56-E868-48DB-B28A-A9F5B7B8702A"
    },
    {
      "class": "text",
      "id": "521F981D-0B29-41B8-A3D2-505985C1DD21"
    },
    {
      "class": "text",
      "id": "2FE01C92-FC04-4843-9162-1BD75AB40715"
    },
    {
      "class": "group",
      "id": "6CD4D309-366D-47A5-9460-CADEC5E23663"
    },
    {
      "class": "shapeGroup",
      "id": "C9F7587C-4F58-43AC-851A-416C5FD01CFE"
    },
    {
      "class": "group",
      "id": "4DCEB84B-4823-4EDD-A8F1-F9790AED8456"
    },
    {
      "class": "group",
      "id": "E4E29301-29E3-42FB-947D-EEA64C35A243"
    },
    {
      "class": "group",
      "id": "3FAD3897-C906-4665-AB2D-099761FCBC54"
    },
    {
      "class": "text",
      "id": "CA37CD19-FD13-401B-AE5F-BBF24AEA884A"
    }
  ],
  "name": "card 4 copy 4",
  "nameIsFixed": true,
  "resizingConstraint": 63,
  "resizingType": 0,
  "rotation": 0,
  "shouldBreakMaskChain": false,
  "style": {
    "_class": "style",
    "endDecorationType": 0,
    "miterLimit": 10,
    "startDecorationType": 0
  }
}