{
  "_class": "group",
  "do_objectID": "3007C719-5ECC-4CC3-9910-428063763426",
  "exportOptions": {
    "_class": "exportOptions",
    "exportFormats": [
    ],
    "includedLayerIds": [
    ],
    "layerOptions": 0,
    "shouldTrim": false
  },
  "frame": {
    "_class": "rect",
    "constrainProportions": false,
    "height": 21,
    "width": 21,
    "x": 324.1593246096163,
    "y": 18.77491847945259
  },
  "hasClickThrough": false,
  "isFlippedHorizontal": false,
  "isFlippedVertical": false,
  "isLocked": false,
  "isVisible": true,
  "layerListExpandedType": 2,
  "layers": [
    {
      "class": "shapeGroup",
      "id": "7C9638F0-4131-41F9-BC94-129C0F4FB9C2"
    },
    {
      "class": "group",
      "id": "1003B024-0441-4F95-8AA6-6C1F35C6A97C"
    }
  ],
  "name": "Oval 31 + ic_clear_black_24px",
  "nameIsFixed": false,
  "resizingConstraint": 63,
  "resizingType": 0,
  "rotation": 0,
  "shouldBreakMaskChain": false,
  "style": {
    "_class": "style",
    "endDecorationType": 0,
    "miterLimit": 10,
    "startDecorationType": 0
  }
}