{
  "_class": "group",
  "do_objectID": "D381F482-2D38-42A6-A8DF-C1D884BAB90F",
  "exportOptions": {
    "_class": "exportOptions",
    "exportFormats": [
    ],
    "includedLayerIds": [
    ],
    "layerOptions": 0,
    "shouldTrim": false
  },
  "frame": {
    "_class": "rect",
    "constrainProportions": false,
    "height": 30,
    "width": 31,
    "x": 0,
    "y": 0
  },
  "hasClickThrough": false,
  "isFlippedHorizontal": false,
  "isFlippedVertical": false,
  "isLocked": false,
  "isVisible": true,
  "layerListExpandedType": 2,
  "layers": [
    {
      "class": "shapeGroup",
      "id": "4E173D2C-9258-41F1-8211-E814D28D1C7C"
    },
    {
      "class": "shapeGroup",
      "id": "F8EABFE0-608F-4453-A073-2EAE0C6A29E6"
    },
    {
      "class": "shapeGroup",
      "id": "48B17381-B501-429B-821F-223B29AA4E44"
    },
    {
      "class": "group",
      "id": "513372B3-ACB9-4CBE-85E1-9FCEAEE1D400"
    },
    {
      "class": "group",
      "id": "FBBC1B5A-D168-459E-B449-7B5935166874"
    },
    {
      "class": "shapeGroup",
      "id": "78EE4C8B-9D27-4B50-B9F2-A19A3020FDB2"
    },
    {
      "class": "shapeGroup",
      "id": "0D205427-8D38-4E4C-B3CB-9089EFA4DAF1"
    }
  ],
  "name": "Group",
  "nameIsFixed": false,
  "resizingConstraint": 63,
  "resizingType": 0,
  "rotation": 0,
  "shouldBreakMaskChain": false,
  "style": {
    "_class": "style",
    "endDecorationType": 0,
    "fills": [
      {
        "_class": "fill",
        "color": {
          "_class": "color",
          "alpha": 1,
          "blue": 0,
          "green": 0,
          "red": 0
        },
        "fillType": 0,
        "isEnabled": true,
        "noiseIndex": 0,
        "noiseIntensity": 0,
        "patternFillType": 1,
        "patternTileScale": 1
      }
    ],
    "miterLimit": 10,
    "startDecorationType": 0
  }
}