{
  "_class": "shapeGroup",
  "clippingMaskMode": 0,
  "do_objectID": "4FCA591A-32AD-45C1-BE58-E988781FF2D0",
  "exportOptions": {
    "_class": "exportOptions",
    "exportFormats": [
    ],
    "includedLayerIds": [
    ],
    "layerOptions": 0,
    "shouldTrim": false
  },
  "frame": {
    "_class": "rect",
    "constrainProportions": false,
    "height": 3,
    "width": 346,
    "x": 0.5,
    "y": 80
  },
  "hasClickThrough": true,
  "hasClippingMask": false,
  "isFlippedHorizontal": false,
  "isFlippedVertical": false,
  "isLocked": false,
  "isVisible": true,
  "layerListExpandedType": 0,
  "layers": [
    {
      "class": "shapePath",
      "id": "CAB2FA09-89F7-4CBE-80A4-C97782749596"
    }
  ],
  "name": "divider",
  "nameIsFixed": true,
  "resizingConstraint": 63,
  "resizingType": 0,
  "rotation": 0,
  "shouldBreakMaskChain": false,
  "style": {
    "_class": "style",
    "borders": [
      {
        "_class": "border",
        "color": {
          "_class": "color",
          "alpha": 0.12,
          "blue": 0,
          "green": 0,
          "red": 0
        },
        "fillType": 0,
        "isEnabled": true,
        "position": 0,
        "thickness": 1
      }
    ],
    "endDecorationType": 0,
    "miterLimit": 10,
    "sharedObjectID": "47256297-ECF7-4051-9671-D57729BEC81F",
    "startDecorationType": 0
  },
  "windingRule": 1
}