{
  "_class": "group",
  "do_objectID": "46172047-B5F0-4436-869D-2AA70C4D6F3F",
  "exportOptions": {
    "_class": "exportOptions",
    "exportFormats": [
    ],
    "includedLayerIds": [
    ],
    "layerOptions": 0,
    "shouldTrim": false
  },
  "frame": {
    "_class": "rect",
    "constrainProportions": false,
    "height": 50,
    "width": 92,
    "x": 0,
    "y": 6.652173913043498
  },
  "hasClickThrough": false,
  "isFlippedHorizontal": false,
  "isFlippedVertical": false,
  "isLocked": false,
  "isVisible": true,
  "layerListExpandedType": 2,
  "layers": [
    {
      "class": "shapeGroup",
      "id": "A2971738-7F30-4735-92B7-004D8A3A6A60"
    },
    {
      "class": "shapeGroup",
      "id": "DDF8F75A-E385-421C-92B0-48BE00F823C4"
    },
    {
      "class": "shapeGroup",
      "id": "D5E8647A-8CED-43EF-9DA5-508C21F52F53"
    },
    {
      "class": "shapeGroup",
      "id": "551EDC6D-35CF-4679-B79D-9378CFA08394"
    },
    {
      "class": "shapeGroup",
      "id": "BEB04B4E-3D59-4150-BFA9-279BA895D4C9"
    },
    {
      "class": "shapeGroup",
      "id": "1F77F0D6-7906-4333-87FC-F248DA59BDEB"
    },
    {
      "class": "shapeGroup",
      "id": "30380742-5B3F-41C1-8656-D8619528D30C"
    }
  ],
  "name": "Group 6",
  "nameIsFixed": false,
  "resizingConstraint": 63,
  "resizingType": 0,
  "rotation": 0,
  "shouldBreakMaskChain": false,
  "style": {
    "_class": "style",
    "endDecorationType": 0,
    "miterLimit": 10,
    "startDecorationType": 0
  }
}