{
  "_class": "shapePath",
  "booleanOperation": -1,
  "do_objectID": "1AEBBEDE-BDEA-458D-84F7-D7A486705A4D",
  "edited": true,
  "exportOptions": {
    "_class": "exportOptions",
    "do_objectID": "35F12C91-18F8-4F18-9EBE-2BDBF450FD0B",
    "exportFormats": [
    ],
    "includedLayerIds": [
    ],
    "layerOptions": 0,
    "shouldTrim": false
  },
  "frame": {
    "_class": "rect",
    "constrainProportions": false,
    "do_objectID": "2CB6575A-6717-4E91-8C32-F599A712EC79",
    "height": 3,
    "width": 955,
    "x": 0,
    "y": 0
  },
  "isClosed": false,
  "isFlippedHorizontal": false,
  "isFlippedVertical": false,
  "isLocked": false,
  "isVisible": true,
  "layerListExpandedType": 0,
  "name": "Path",
  "nameIsFixed": false,
  "pointRadiusBehaviour": 1,
  "points": [
    {
      "_class": "curvePoint",
      "cornerRadius": 0,
      "curveFrom": "{0.0052356020942408406, 0.66666666666666663}",
      "curveMode": 1,
      "curveTo": "{0.0052356020942408406, 0.66666666666666663}",
      "hasCurveFrom": false,
      "hasCurveTo": false,
      "point": "{0.00052356020942408382, 0.5}"
    },
    {
      "_class": "curvePoint",
      "cornerRadius": 0,
      "curveFrom": "{0.0062827225130890098, 1}",
      "curveMode": 1,
      "curveTo": "{0.0062827225130890098, 1}",
      "hasCurveFrom": false,
      "hasCurveTo": false,
      "point": "{0.99947643979057599, 0.5}"
    }
  ],
  "resizingConstraint": 63,
  "resizingType": 0,
  "rotation": 0,
  "shouldBreakMaskChain": false
}