{
  "_class": "shapeGroup",
  "clippingMaskMode": 0,
  "do_objectID": "2D750B27-54D9-4796-B44D-1C7303A40BA2",
  "exportOptions": {
    "_class": "exportOptions",
    "do_objectID": "72A3466D-76E4-43BF-97CC-C4851759DD83",
    "exportFormats": [
    ],
    "includedLayerIds": [
    ],
    "layerOptions": 0,
    "shouldTrim": false
  },
  "frame": {
    "_class": "rect",
    "constrainProportions": false,
    "do_objectID": "7A2648D3-3A9C-440D-9495-C09172A57A3F",
    "height": 592,
    "width": 253,
    "x": 0,
    "y": 0
  },
  "hasClickThrough": true,
  "hasClippingMask": false,
  "isFlippedHorizontal": false,
  "isFlippedVertical": false,
  "isLocked": false,
  "isVisible": true,
  "layerListExpandedType": 1,
  "layers": [
    {
      "class": "rectangle",
      "id": "A5395BB3-28E0-4199-942B-63F0D6A48638"
    }
  ],
  "name": "drawer bg",
  "nameIsFixed": true,
  "resizingConstraint": 63,
  "resizingType": 0,
  "rotation": 0,
  "shouldBreakMaskChain": false,
  "style": {
    "_class": "style",
    "do_objectID": "0D3A3FC9-BF8F-4A79-8A08-3BEB590256A8",
    "endDecorationType": 0,
    "fills": [
      {
        "_class": "fill",
        "color": {
          "_class": "color",
          "alpha": 1,
          "blue": 0.2,
          "green": 0.2,
          "red": 0.2
        },
        "fillType": 0,
        "isEnabled": true,
        "noiseIndex": 0,
        "noiseIntensity": 0,
        "patternFillType": 0,
        "patternTileScale": 1
      }
    ],
    "miterLimit": 10,
    "shadows": [
      {
        "_class": "shadow",
        "blurRadius": 16,
        "color": {
          "_class": "color",
          "alpha": 0.24,
          "blue": 0,
          "green": 0,
          "red": 0
        },
        "contextSettings": {
          "_class": "graphicsContextSettings",
          "blendMode": 0,
          "opacity": 1
        },
        "do_objectID": "BD65D43B-12E3-4D48-8D33-A61EF60FCA48",
        "isEnabled": true,
        "offsetX": 0,
        "offsetY": 16,
        "spread": 0
      },
      {
        "_class": "shadow",
        "blurRadius": 16,
        "color": {
          "_class": "color",
          "alpha": 0.18,
          "blue": 0,
          "green": 0,
          "red": 0
        },
        "contextSettings": {
          "_class": "graphicsContextSettings",
          "blendMode": 0,
          "opacity": 1
        },
        "do_objectID": "8B1CAEE6-5AB0-4396-95E0-29FD7D78072E",
        "isEnabled": true,
        "offsetX": 0,
        "offsetY": 0,
        "spread": 0
      }
    ],
    "startDecorationType": 0
  },
  "userInfo": {
    "com.animaapp.stc-sketch-plugin": {
      "kModelPropertiesKey": {
      }
    }
  },
  "windingRule": 1
}