{
  "_class": "group",
  "do_objectID": "23CF327C-13EA-46DA-AED9-495751788B9C",
  "exportOptions": {
    "_class": "exportOptions",
    "exportFormats": [
    ],
    "includedLayerIds": [
    ],
    "layerOptions": 0,
    "shouldTrim": false
  },
  "frame": {
    "_class": "rect",
    "constrainProportions": false,
    "height": 44,
    "width": 375,
    "x": 0,
    "y": 182
  },
  "hasClickThrough": false,
  "isFlippedHorizontal": false,
  "isFlippedVertical": false,
  "isLocked": false,
  "isVisible": true,
  "layerListExpandedType": 2,
  "layers": [
    {
      "class": "shapeGroup",
      "id": "1B48EB55-CF78-4ECC-BAC6-DF976556EE57"
    },
    {
      "class": "shapeGroup",
      "id": "764E8135-F182-444A-8B5D-731BA3F5871F"
    },
    {
      "class": "shapeGroup",
      "id": "6C17751F-B3B9-4F5A-8E08-581FD9A411D5"
    },
    {
      "class": "text",
      "id": "EC858B58-A315-4C36-BCAB-A926AD4A12A2"
    }
  ],
  "name": "Cells/Table/Cell Copy 2",
  "nameIsFixed": false,
  "resizingConstraint": 63,
  "resizingType": 0,
  "rotation": 0,
  "shouldBreakMaskChain": false,
  "style": {
    "_class": "style",
    "endDecorationType": 0,
    "miterLimit": 10,
    "startDecorationType": 0
  },
  "userInfo": {
    "com.animaapp.stc-sketch-plugin": {
      "kModelPropertiesKey": {
      }
    }
  }
}