{
  "_class": "shapeGroup",
  "clippingMaskMode": 0,
  "do_objectID": "52A131A5-EB21-4017-9A72-BAB5A11F4AA3",
  "exportOptions": {
    "_class": "exportOptions",
    "do_objectID": "19ACBC95-44F3-4612-BF4A-97E1195463E2",
    "exportFormats": [
    ],
    "includedLayerIds": [
    ],
    "layerOptions": 0,
    "shouldTrim": false
  },
  "frame": {
    "_class": "rect",
    "constrainProportions": false,
    "do_objectID": "FFD7D345-DA2C-4947-80E1-8EC169DCEBF7",
    "height": 128,
    "width": 2435,
    "x": 5936,
    "y": -212
  },
  "hasClickThrough": false,
  "hasClippingMask": false,
  "isFlippedHorizontal": false,
  "isFlippedVertical": false,
  "isLocked": false,
  "isVisible": true,
  "layerListExpandedType": 1,
  "layers": [
    {
      "class": "rectangle",
      "id": "04A29B38-2855-4930-88A9-8EE85C929048"
    }
  ],
  "name": "Rectangle 4 Copy 4",
  "nameIsFixed": false,
  "resizingConstraint": 63,
  "resizingType": 0,
  "rotation": 0,
  "shouldBreakMaskChain": false,
  "style": {
    "_class": "style",
    "borders": [
      {
        "_class": "border",
        "color": {
          "_class": "color",
          "alpha": 1,
          "blue": 0.592,
          "green": 0.592,
          "red": 0.592
        },
        "fillType": 0,
        "isEnabled": false,
        "position": 1,
        "thickness": 1
      }
    ],
    "do_objectID": "C56AD1A9-326C-49A4-8219-1CCE71117B6E",
    "endDecorationType": 0,
    "fills": [
      {
        "_class": "fill",
        "color": {
          "_class": "color",
          "alpha": 1,
          "blue": 0.8117647058823529,
          "green": 0.7450980392156861,
          "red": 0.3019607843137256
        },
        "fillType": 0,
        "isEnabled": true,
        "noiseIndex": 0,
        "noiseIntensity": 0,
        "patternFillType": 0,
        "patternTileScale": 1
      }
    ],
    "miterLimit": 10,
    "startDecorationType": 0
  },
  "userInfo": {
    "com.animaapp.stc-sketch-plugin": {
      "kModelPropertiesKey": {
      }
    }
  },
  "windingRule": 1
}